odoo/addons/sale_stock_partner_warehouse/README.rst
odoo/addons/sale_stock_partner_warehouse/__init__.py
odoo/addons/sale_stock_partner_warehouse/__manifest__.py
odoo/addons/sale_stock_partner_warehouse/i18n/ca.po
odoo/addons/sale_stock_partner_warehouse/i18n/es.po
odoo/addons/sale_stock_partner_warehouse/i18n/it.po
odoo/addons/sale_stock_partner_warehouse/i18n/sale_stock_partner_warehouse.pot
odoo/addons/sale_stock_partner_warehouse/models/__init__.py
odoo/addons/sale_stock_partner_warehouse/models/res_partner.py
odoo/addons/sale_stock_partner_warehouse/models/sale_order.py
odoo/addons/sale_stock_partner_warehouse/readme/CONFIGURE.md
odoo/addons/sale_stock_partner_warehouse/readme/CONTRIBUTORS.md
odoo/addons/sale_stock_partner_warehouse/readme/DESCRIPTION.md
odoo/addons/sale_stock_partner_warehouse/readme/USAGE.md
odoo/addons/sale_stock_partner_warehouse/static/description/icon.png
odoo/addons/sale_stock_partner_warehouse/static/description/index.html
odoo/addons/sale_stock_partner_warehouse/tests/__init__.py
odoo/addons/sale_stock_partner_warehouse/tests/test_sale_stock_partner_warehouse.py
odoo/addons/sale_stock_partner_warehouse/views/partner_view.xml
odoo_addon_sale_stock_partner_warehouse-18.0.1.0.0.3.dist-info/METADATA
odoo_addon_sale_stock_partner_warehouse-18.0.1.0.0.3.dist-info/WHEEL
odoo_addon_sale_stock_partner_warehouse-18.0.1.0.0.3.dist-info/top_level.txt
odoo_addon_sale_stock_partner_warehouse-18.0.1.0.0.3.dist-info/RECORD
